[{"image_id": "1_IM-0001-4001.png", "caption": [["<start>", "there", "size", "and"]]}, {"image_id": "20_IM-0653-1001.png", "caption": [["<start>", "the", "and", "mediastinal", "within", "within", "normal", "and", "mediastinal", "ap", "silhouette", "appearance", "size"]]}, {"image_id": "39_IM-1978-1001.png", "caption": [["<start>", "heart", "and", "silhouette"]]}, {"image_id": "62_IM-2202-4004.png", "caption": [["<start>", "the", "heart", "size"]]}, {"image_id": "85_IM-2372-1001.png", "caption": [["<start>", "lungs", "size", "clear", "is", "normal", "normal", "heart", "no", "are", "tortuous", "pulmonary", "airspace"]]}, {"image_id": "105_IM-0037-2001.png", "caption": [["<start>", "the", "are", "and", "views", "atelectasis", "size", "consistent", "infiltrates", "lower", "consolidation", "markings"]]}, {"image_id": "127_IM-0181-1001.png", "caption": [["<start>", "the", "heart", "size"]]}, {"image_id": "152_IM-0335-2001.png", "caption": [["<start>", "cardiomediastinal", "are"]]}, {"image_id": "176_IM-0496-1001.png", "caption": [["<start>", "there", "size"]]}, {"image_id": "197_IM-0631-1001.png", "caption": [["<start>", "low", "lungs", "is", "contours", "in", "within"]]}, {"image_id": "223_IM-0831-1001.png", "caption": [["<start>"]]}, {"image_id": "248_IM-1008-85149003.png", "caption": [["<start>", "the", "focal", "are"]]}, {"image_id": "266_IM-1141-2001.png", "caption": [["<start>", "heart", "and", "unchanged", "clear", "contours", "are", "focal", "in", "and", "significantly"]]}, {"image_id": "283_IM-1248-2001.png", "caption": [["<start>", "the", "lungs", "hyperexpanded", "within", "pleural", "heart"]]}, {"image_id": "306_IM-1426-1001.png", "caption": [["<start>", "lungs", "are", "is", "views", "lower", "of", "of", "has", "abnormality"]]}, {"image_id": "330_IM-1577-0001-0002.png", "caption": [["<start>", "the", "and", "pulmonary", "clear", "moderately", "normal", "normal", "acute", "effusion", "is", "heart", "there", "and", "lungs", "hemidiaphragm", "structures", "effusion", "healed", "hyperexpansion", "or", "size", "bony"]]}, {"image_id": "347_IM-1686-1001.png", "caption": [["<start>", "the", "cardiac", "normal", "a", "no", "there"]]}, {"image_id": "365_IM-1812-1001.png", "caption": [["<start>", "the", "cardiac", "and", "mediastinal", "bilaterally", "within", "effusion", "in"]]}, {"image_id": "387_IM-1962-2001.png", "caption": [["<start>", "borderline", "size", "stable", "is", "contours", "calcifications", "clear", "normal"]]}, {"image_id": "405_IM-2053-2001.png", "caption": [["<start>", "there", "are"]]}, {"image_id": "428_IM-2070-1001.png", "caption": [["<start>", "radiographic", "size", "is", "appear"]]}, {"image_id": "452_IM-2083-3003.png", "caption": [["<start>", "stable", "enlarged", "diaphragm"]]}, {"image_id": "475_IM-2101-1001.png", "caption": [["<start>", "lungs", "are", "and", "mild", "atelectasis", "heart", "normal", "limits", "crowding", "and", "unremarkable", "no", "clear"]]}, {"image_id": "495_IM-2114-1001.png", "caption": [["<start>", "the", "heart", "cardiac", "is", "atrium", "subtle", "specifically", "normal", "are", "the", "left", "the", "airspace", "the", "effusion", "intact", "there"]]}, {"image_id": "515_IM-2129-2001.png", "caption": [["<start>", "the", "size", "are"]]}, {"image_id": "539_IM-2145-2001.png", "caption": [["<start>", "heart", "images", "configuration", "mild", "obtained", "the", "and", "with", "and", "and", "lungs", "within"]]}, {"image_id": "562_IM-2163-1001.png", "caption": [["<start>", "normal", "heart", "is", "clear", "the", "within", "effusion", "the"]]}, {"image_id": "587_IM-2182-3001.png", "caption": [["<start>", "lungs", "for", "size", "clear"]]}, {"image_id": "613_IM-2200-1001.png", "caption": [["<start>", "contour"]]}, {"image_id": "632_IM-2213-1001.png", "caption": [["<start>", "no", "size", "and", "clear", "pneumothorax", "with", "cardiac", "the", "noncalcified", "central", "within", "focal", "focal", "effusion", "no", "focal"]]}, {"image_id": "657_IM-2233-0001-0002.png", "caption": [["<start>", "the", "technical", "and", "is"]]}, {"image_id": "679_IM-2251-2001.png", "caption": [["<start>", "the", "lungs", "disease", "normal", "is", "lung", "and", "pulmonary", "the", "within", "ectatic", "abdomen", "free", "is", "silhouettes", "lungs", "effusions"]]}, {"image_id": "700_IM-2265-4004.png", "caption": [["<start>", "the", "heart", "and", "without", "normal", "there", "within", "acute", "both", "scattered", "of", "no", "pneumothorax", "is", "and"]]}, {"image_id": "723_IM-2283-1001.png", "caption": [["<start>", "the", "focal", "is", "hyperexpanded", "normal"]]}, {"image_id": "746_IM-2300-3001.png", "caption": [["<start>", "low", "lungs", "and"]]}, {"image_id": "765_IM-2311-2001.png", "caption": [["<start>", "the"]]}, {"image_id": "784_IM-2325-1001-0001.png", "caption": [["<start>", "the", "size", "normal", "is"]]}, {"image_id": "809_IM-2342-1001.png", "caption": [["<start>", "lungs", "size", "is", "normal"]]}, {"image_id": "831_IM-2358-4004.png", "caption": [["<start>", "the", "heart", "examination", "and", "normal", "normal", "the", "pulmonary", "the", "focal", "no", "configuration"]]}, {"image_id": "850_IM-2373-0001-0003.png", "caption": [["<start>", "lungs", "lungs", "heart", "normal", "deformity", "are", "cardiomegaly", "consistent", "visible", "the", "effusion"]]}, {"image_id": "875_IM-2392-1001.png", "caption": [["<start>", "heart", "lungs", "are", "within", "contour", "size"]]}, {"image_id": "901_IM-2409-3001.png", "caption": [["<start>", "the", "heart", "clear", "enlarged", "no", "vascularity", "mediastinum", "within", "size", "mediastinum", "focal", "pulmonary", "cardiac", "airspace"]]}, {"image_id": "921_IM-2423-2001.png", "caption": [["<start>", "no", "are", "clear", "at", "contours", "size", "and", "lower", "no", "interval", "the", "thoracic", "limits"]]}, {"image_id": "941_IM-2438-1001.png", "caption": [["<start>", "the", "heart", "is", "mild", "mediastinal", "with", "cardiomediastinal"]]}, {"image_id": "960_IM-2451-4004.png", "caption": [["<start>", "normal", "is", "silhouette"]]}, {"image_id": "979_IM-2466-1001.png", "caption": [["<start>", "the", "heart", "is", "mediastinal", "calcified", "size"]]}, {"image_id": "999_IM-2480-1001.png", "caption": [["<start>", "mediastinal", "lungs", "of"]]}, {"image_id": "1019_IM-0015-2001.png", "caption": [["<start>", "the", "lungs", "clear", "normal", "clear", "the"]]}, {"image_id": "1042_IM-0034-3001.png", "caption": [["<start>", "heart", "and", "mildly", "midline", "within", "unremarkable", "effusions", "mediastinal", "left", "mediastinum", "or", "infiltrate", "consolidation", "normal"]]}, {"image_id": "1059_IM-0041-1001.png", "caption": [["<start>", "the", "heart", "of", "within"]]}, {"image_id": "1083_IM-0058-2001.png", "caption": [["<start>", "the", "heart", "size", "normal", "are"]]}, {"image_id": "1102_IM-0069-2001.png", "caption": [["<start>", "there", "cardiomegaly", "normal", "heart", "normal", "clear", "the", "limits", "contour", "are", "are", "no", "is", "limits", "bony", "spondylosis"]]}, {"image_id": "1122_IM-0080-1001-0001.png", "caption": [["<start>", "heart", "focal", "examination", "right", "there", "emphysema", "catheter"]]}, {"image_id": "1148_IM-0100-1001.png", "caption": [["<start>", "the", "heart", "contours", "spaces", "normal", "lungs"]]}, {"image_id": "1170_IM-0115-3001.png", "caption": [["<start>", "chronic", "heart", "lobe"]]}, {"image_id": "1192_IM-0129-2001.png", "caption": [["<start>", "the", "are", "is", "is"]]}, {"image_id": "1212_IM-0143-1001.png", "caption": [["<start>", "right", "spaces"]]}, {"image_id": "1234_IM-0157-4004.png", "caption": [["<start>", "the", "mediastinal", "mildly", "tortuous", "calcification", "mild", "seen"]]}, {"image_id": "1259_IM-0175-1001.png", "caption": [["<start>", "the", "hyperexpanded", "are", "and", "pulmonary", "are", "clear", "in", "lesions"]]}, {"image_id": "1277_IM-0185-1001.png", "caption": [["<start>", "the", "pneumothorax", "are", "and"]]}, {"image_id": "1302_IM-0198-2001.png", "caption": [["<start>", "heart", "lungs", "and"]]}, {"image_id": "1324_IM-0209-2001.png", "caption": [["<start>", "hyperinflated", "cardiomediastinal", "normal", "is", "of", "contours"]]}, {"image_id": "1347_IM-0225-4004.png", "caption": [["<start>", "mild", "size", "clear", "with"]]}, {"image_id": "1368_IM-0237-1001.png", "caption": [["<start>", "heart", "cardiomediastinal", "are", "pleural", "calcified", "vascularity", "focal", "lungs", "pulmonary", "pleural"]]}, {"image_id": "1386_IM-0246-1001.png", "caption": [["<start>", "normal", "heart", "of"]]}, {"image_id": "1407_IM-0260-2001.png", "caption": [["<start>", "no", "is", "granulomas", "clear", "well", "are", "mediastinum", "are", "at", "the", "of"]]}, {"image_id": "1430_IM-0277-2001.png", "caption": [["<start>", "right", "lungs", "are", "clear"]]}, {"image_id": "1452_IM-0291-2001.png", "caption": [["<start>", "mediastinal", "pneumothorax", "focal"]]}, {"image_id": "1469_IM-0303-2001.png", "caption": [["<start>", "the", "and", "the", "acute"]]}, {"image_id": "1489_IM-0315-1001.png", "caption": [["<start>", "the", "heart"]]}, {"image_id": "1516_IM-0334-2001.png", "caption": [["<start>", "the", "patchy", "is", "clear", "are", "there", "otherwise", "consolidation", "tip", "evidence", "are", "pneumothorax", "there"]]}, {"image_id": "1537_IM-0348-1001.png", "caption": [["<start>", "the", "size", "lateral"]]}, {"image_id": "1554_IM-0361-1002.png", "caption": [["<start>", "heart", "heart", "no", "of", "elevation", "unchanged", "cardiomediastinal", "lateral", "mediastinum", "is", "focal", "pulmonary", "the", "pneumonia", "hypoinflated", "of", "lungs", "consolidation", "pleural", "focal", "markings", "or", "effusion", "line", "pneumothorax", "is"]]}, {"image_id": "1576_IM-0375-2001.png", "caption": [["<start>", "lungs", "heart", "normal"]]}, {"image_id": "1595_IM-0386-1001.png", "caption": [["<start>", "without", "lungs", "are", "effusion", "normal", "by", "limits", "interstitial"]]}, {"image_id": "1621_IM-0403-1002.png", "caption": [["<start>", "there", "heart", "is", "the", "airspace", "within", "consolidation", "within", "pneumothorax", "limits", "or", "pleural", "expanded", "are", "normal", "normal", "scarring", "in", "pleural"]]}, {"image_id": "1639_IM-0418-5001.png", "caption": [["<start>", "pneumothorax", "cardiomediastinal", "size", "normal"]]}, {"image_id": "1659_IM-0434-1002.png", "caption": [["<start>", "there", "cardiomediastinal", "normal", "midline", "lobe", "are", "masses", "and"]]}, {"image_id": "1679_IM-0448-1002.png", "caption": [["<start>", "the", "normal", "clear", "bilaterally", "pulmonary", "left"]]}, {"image_id": "1705_IM-0465-2001.png", "caption": [["<start>", "the", "lungs", "are", "healed", "size", "view", "appear", "pulmonary", "no", "the", "cardiac"]]}, {"image_id": "1729_IM-0480-1001.png", "caption": [["<start>", "normal", "size", "is", "normal", "limits", "osseous", "of"]]}, {"image_id": "1753_IM-0494-1001.png", "caption": [["<start>", "the", "heart", "and", "and", "tortuous", "within"]]}, {"image_id": "1779_IM-0509-1002.png", "caption": [["<start>", "there", "heart", "size", "moderate", "chest"]]}, {"image_id": "1801_IM-0520-2001.png", "caption": [["<start>", "normal", "lungs", "are", "unchanged", "evidence", "was", "lungs", "have", "heart", "alveolar"]]}, {"image_id": "1831_IM-0538-3001.png", "caption": [["<start>", "the", "and", "is", "clear", "and", "are", "of", "or", "and", "is"]]}, {"image_id": "1853_IM-0555-2001.png", "caption": [["<start>", "the", "cardiac", "silhouette"]]}, {"image_id": "1877_IM-0568-2001.png", "caption": [["<start>", "no", "silhouettes", "with", "normal"]]}, {"image_id": "1895_IM-0581-2001.png", "caption": [["<start>", "normal", "lungs", "is", "normal", "silhouettes", "represent", "grossly", "and", "the"]]}, {"image_id": "1919_IM-0598-2001.png", "caption": [["<start>", "there", "cardiomediastinal", "volumes", "clear"]]}, {"image_id": "1935_IM-0605-0001-0002.png", "caption": [["<start>", "there", "lungs", "size"]]}, {"image_id": "1957_IM-0624-0001.png", "caption": [["<start>", "the", "or", "midline", "normal", "no", "of", "the"]]}, {"image_id": "1978_IM-0636-2001.png", "caption": [["<start>", "the", "focal", "are", "and", "normal", "focal"]]}, {"image_id": "2003_IM-0654-2001.png", "caption": [["<start>", "mediastinal", "cardiac", "size", "enlarged", "vasculature", "there", "radiographs", "pulmonary", "heart", "limits", "in", "are", "or", "airspace"]]}, {"image_id": "2025_IM-0671-1002.png", "caption": [["<start>", "the", "heart", "silhouette", "mediastinum", "appear", "change", "free", "silhouette"]]}, {"image_id": "2047_IM-0688-1002.png", "caption": [["<start>", "frontal", "and", "again", "bibasilar", "size", "limits", "lungs", "the", "size", "hiatal", "is", "mild", "pleural"]]}, {"image_id": "2074_IM-0708-2001.png", "caption": [["<start>", "heart", "heart", "are", "focal"]]}, {"image_id": "2097_IM-0727-1001-0001.png", "caption": [["<start>", "the", "heart", "lungs"]]}, {"image_id": "2120_IM-0747-1001.png", "caption": [["<start>", "heart", "heart", "clear", "granulomas", "in", "are"]]}, {"image_id": "2146_IM-0766-13013.png", "caption": [["<start>", "low", "are", "areas", "pleural", "noted", "vascularity", "lungs", "no", "effusions", "appear", "soft", "focal", "the", "no", "normal", "or", "mediastinum", "are", "contours", "and", "or", "airspace", "thoracic", "are"]]}, {"image_id": "2167_IM-0783-1001.png", "caption": [["<start>", "normal", "in", "silhouette", "contours", "spaces", "of", "limits", "heart", "tissues", "are", "the", "no"]]}, {"image_id": "2191_IM-0801-1001.png", "caption": [["<start>", "calcified", "of", "are", "are", "again", "expanded", "cardiomediastinal", "negative"]]}, {"image_id": "2213_IM-0819-1001.png", "caption": [["<start>", "cardiac", "cardiac", "and", "have", "size"]]}, {"image_id": "2239_IM-0836-2001.png", "caption": [["<start>", "heart", "are", "chest", "is", "pulmonary", "and", "airspace", "normal", "pneumothorax", "right", "is", "size", "body", "the", "of"]]}, {"image_id": "2260_IM-0852-2001.png", "caption": [["<start>", "the", "heart", "is", "is", "patchy", "free", "in"]]}, {"image_id": "2288_IM-0872-1001.png", "caption": [["<start>", "there", "lungs", "is", "size", "are", "enlarged", "pneumothorax", "within", "normal", "normal", "pneumothorax", "silhouette", "a", "markings", "without"]]}, {"image_id": "2307_IM-0882-1001.png", "caption": [["<start>", "there", "are", "within", "is", "in"]]}, {"image_id": "2328_IM-0898-2001.png", "caption": [["<start>", "lateral", "heart", "silhouette", "lung", "lymph", "normal"]]}, {"image_id": "2351_IM-0917-1001.png", "caption": [["<start>", "cardiomediastinal", "lungs", "size", "is"]]}, {"image_id": "2372_IM-0933-0001-0001.png", "caption": [["<start>", "heart", "heart", "are", "within", "lungs", "normal", "the", "mild", "normal", "are", "bibasilar"]]}, {"image_id": "2394_IM-0944-2001.png", "caption": [["<start>", "heart", "lungs", "size", "with", "the", "limits", "mediastinum", "rib", "vasculature", "pleural", "pleural", "the", "the", "lungs", "pneumothorax", "are", "grossly", "within"]]}, {"image_id": "2417_IM-0961-1001.png", "caption": [["<start>", "the", "heart", "and", "previous", "mediastinum", "of"]]}, {"image_id": "2440_IM-0978-2001.png", "caption": [["<start>", "heart", "size", "clear", "consists", "pulmonary"]]}, {"image_id": "2462_IM-0995-1001.png", "caption": [["<start>", "no", "lung", "silhouette", "clear"]]}, {"image_id": "2484_IM-1012-2001.png", "caption": [["<start>", "the", "cardiomediastinal", "within", "normal"]]}, {"image_id": "2514_IM-1036-1001.png", "caption": [["<start>", "the", "areas", "are", "is", "normal", "view", "focal", "the", "no", "lungs", "effusion", "there"]]}, {"image_id": "2538_IM-1050-1002.png", "caption": [["<start>", "lungs", "cardiomediastinal", "is"]]}, {"image_id": "2559_IM-1063-3003.png", "caption": [["<start>", "heart", "cardiomediastinal", "and", "opacity", "in", "clear", "no", "soft", "vascularity", "limits", "or", "size", "consolidation", "opacity", "is", "reveal", "effusion"]]}, {"image_id": "2584_IM-1081-2001.png", "caption": [["<start>", "heart", "are", "is", "mediastinal", "noted", "bronchovascular", "structures"]]}, {"image_id": "2612_IM-1103-2001.png", "caption": [["<start>", "atelectasis", "of", "are", "radiograph", "limits", "vasculature"]]}, {"image_id": "2635_IM-1121-2001.png", "caption": [["<start>", "are", "size", "size"]]}, {"image_id": "2658_IM-1140-2001.png", "caption": [["<start>", "heart", "size", "and", "bony", "and", "no"]]}, {"image_id": "2684_IM-1157-1001.png", "caption": [["<start>", "the", "cardiac", "are", "heart", "marked", "in", "are", "within", "flattening", "mediastinal", "markings", "pulmonary", "the", "effusions", "left"]]}, {"image_id": "2709_IM-1175-1001.png", "caption": [["<start>", "heart", "cardiomediastinal", "is", "mediastinal", "silhouette", "expanded", "normal", "focal", "pulmonary"]]}, {"image_id": "2728_IM-1187-1001.png", "caption": [["<start>", "the", "lungs"]]}, {"image_id": "2749_IM-1199-1002.png", "caption": [["<start>", "frontal", "size", "suggestive", "normal"]]}, {"image_id": "2774_IM-1215-2001.png", "caption": [["<start>", "heart", "cardiac", "is", "consolidation", "leads"]]}, {"image_id": "2793_IM-1226-2001.png", "caption": [["<start>", "show", "heart", "size", "and"]]}, {"image_id": "2815_IM-1240-1001.png", "caption": [["<start>", "the", "cardiomediastinal", "lateral", "is", "are", "unremarkable", "is"]]}, {"image_id": "2839_IM-1252-1001.png", "caption": [["<start>", "the", "heart", "and", "normal", "clear", "in", "within", "of", "structures", "focal"]]}, {"image_id": "2860_IM-1268-1002.png", "caption": [["<start>", "the", "size", "is", "normal", "vascularity", "and", "appear"]]}, {"image_id": "2885_IM-1287-2001.png", "caption": [["<start>", "the", "lungs"]]}, {"image_id": "2904_IM-1308-3001.png", "caption": [["<start>", "disease", "heart", "hyperexpanded"]]}, {"image_id": "2929_IM-1331-1001.png", "caption": [["<start>", "the", "is", "size"]]}, {"image_id": "2946_IM-1346-1001.png", "caption": [["<start>", "there", "size", "are", "pleural", "pneumothorax", "is"]]}, {"image_id": "2967_IM-1360-1001.png", "caption": [["<start>", "the", "heart", "a", "mediastinum", "normal", "are", "stable", "contour", "infiltrate"]]}, {"image_id": "2992_IM-1379-2002.png", "caption": [["<start>", "is", "and"]]}, {"image_id": "3015_IM-1392-1001.png", "caption": [["<start>", "there", "lung", "silhouette", "clear", "normal", "are"]]}, {"image_id": "3040_IM-1414-12012.png", "caption": [["<start>", "the", "cardiomediastinal", "this", "and", "in", "limits", "size", "large", "vascularity", "effusions", "heart"]]}, {"image_id": "3062_IM-1428-1001.png", "caption": [["<start>", "the", "cardiomediastinal", "size", "is", "size", "cardiac", "without", "mediastinal", "over", "no", "right", "a", "or", "quadrant", "are", "focal"]]}, {"image_id": "3081_IM-1440-1002.png", "caption": [["<start>", "lungs", "and", "size", "clear", "no"]]}, {"image_id": "3099_IM-1450-1001.png", "caption": [["<start>", "the", "of", "are", "is", "lobe", "in", "are", "pneumothorax", "are", "left", "unremarkable", "pleura", "effusion", "heart", "of", "there"]]}, {"image_id": "3117_IM-1465-2001.png", "caption": [["<start>", "heart", "heart", "clear", "and", "calcified"]]}, {"image_id": "3135_IM-1474-2001.png", "caption": [["<start>", "the", "cardiomediastinal", "is"]]}, {"image_id": "3159_IM-1487-1001-0001.png", "caption": [["<start>", "the", "cardiomediastinal", "are", "effusion", "evaluation", "within", "and", "heart", "focal", "contour", "patchy", "is", "cardiac", "lungs", "are", "and"]]}, {"image_id": "3180_IM-1500-2001.png", "caption": [["<start>", "the", "heart", "normal", "abnormality", "and", "with", "spondylosis", "no"]]}, {"image_id": "3203_IM-1513-1001.png", "caption": [["<start>", "the", "heart", "clear", "contours", "contour", "show", "specifically"]]}, {"image_id": "3222_IM-1522-1001.png", "caption": [["<start>", "cardiac", "focal", "is", "clear"]]}, {"image_id": "3242_IM-1534-1002.png", "caption": [["<start>", "there", "size", "is", "enlarged", "in", "scarring", "no", "within", "contour", "evidence", "limits"]]}, {"image_id": "3262_IM-1548-2001.png", "caption": [["<start>", "the", "lungs", "and", "airspace", "contour", "are", "no", "the", "within", "the", "within", "both", "limits"]]}, {"image_id": "3282_IM-1563-1001.png", "caption": [["<start>", "the", "mediastinal", "size", "and", "enlarged", "hernia", "or", "are", "mediastinal", "silhouette"]]}, {"image_id": "3301_IM-1579-1001.png", "caption": [["<start>", "stable", "heart", "of", "lungs", "no", "middle", "airspace"]]}, {"image_id": "3319_IM-1588-2001.png", "caption": [["<start>", "heart", "cardiomediastinal", "and", "consists", "size", "limits", "the", "or", "no", "consolidation", "stable", "loss", "no", "airspace", "or", "focal", "is", "contour", "pneumothorax", "there", "limits", "well"]]}, {"image_id": "3345_IM-1603-1001.png", "caption": [["<start>", "is", "heart", "no", "lateral", "or", "the", "within"]]}, {"image_id": "3363_IM-1616-1002.png", "caption": [["<start>", "the", "are", "upper", "clear", "in", "size", "lungs", "focal", "lungs", "no", "contours", "lungs", "bony", "remain", "mildly", "cardiomediastinal"]]}, {"image_id": "3385_IM-1632-2001.png", "caption": [["<start>", "there", "and", "and", "of"]]}, {"image_id": "3404_IM-1647-2001.png", "caption": [["<start>"]]}, {"image_id": "3423_IM-1656-1001.png", "caption": [["<start>", "the", "distal", "bilateral", "and", "size", "vasculature", "no", "mid", "atherosclerotic", "limits", "of"]]}, {"image_id": "3445_IM-1668-3001.png", "caption": [["<start>", "stable", "size", "low"]]}, {"image_id": "3467_IM-1684-0001-0001.png", "caption": [["<start>", "mediastinal", "examination"]]}, {"image_id": "3486_IM-1695-1001.png", "caption": [["<start>", "the", "heart", "size"]]}, {"image_id": "3507_IM-1709-4004.png", "caption": [["<start>", "there", "compared", "and"]]}, {"image_id": "3525_IM-1722-1001.png", "caption": [["<start>", "the", "heart", "are"]]}, {"image_id": "3545_IM-1737-2002.png", "caption": [["<start>", "the", "lungs", "old", "normal"]]}, {"image_id": "3565_IM-1750-1001.png", "caption": [["<start>", "there", "cardiomediastinal", "a", "pulmonary", "in"]]}, {"image_id": "3581_IM-1761-3001.png", "caption": [["<start>", "clear", "cardiomediastinal", "silhouette", "borderline", "normal", "the", "clear"]]}, {"image_id": "3602_IM-1778-2001.png", "caption": [["<start>", "lung"]]}, {"image_id": "3627_IM-1795-2001.png", "caption": [["<start>", "pa", "heart", "silhouette", "lungs", "in", "size", "the", "no", "no", "are", "is"]]}, {"image_id": "3649_IM-1811-3001.png", "caption": [["<start>", "pneumothorax", "and", "aorta", "are", "with", "within"]]}, {"image_id": "3666_IM-1824-3001.png", "caption": [["<start>", "the", "cardiomediastinal"]]}, {"image_id": "3693_IM-1844-1001.png", "caption": [["<start>", "heart", "moderate", "lateral", "and", "vascularity", "lingula", "there", "granulomas", "normal", "there", "contour", "with", "pleural", "heart", "the", "nodule"]]}, {"image_id": "3716_IM-1856-1001.png", "caption": [["<start>", "the", "and", "is", "mild", "volumes", "there", "and", "focal", "degenerative", "the", "pleural", "or", "are", "pneumothorax"]]}, {"image_id": "3737_IM-1867-2001.png", "caption": [["<start>", "heart", "heart", "is"]]}, {"image_id": "3757_IM-1881-2001.png", "caption": [["<start>", "no", "are", "is", "of"]]}, {"image_id": "3778_IM-1894-1001.png", "caption": [["<start>", "the", "lungs", "silhouette", "large", "vasculature", "vasculature", "elevated", "pleural", "vascularity", "clear", "there"]]}, {"image_id": "3803_IM-1913-3001.png", "caption": [["<start>", "the", "size", "clear", "and", "size", "are", "and", "frontal", "normal", "are", "is", "pulmonary", "limits", "are", "the"]]}, {"image_id": "3826_IM-1932-2001.png", "caption": [["<start>", "the", "heart", "are", "bilaterally", "contours", "are", "and"]]}, {"image_id": "3846_IM-1946-1001.png", "caption": [["<start>", "stable", "and", "normal", "normal", "limits", "are", "airspace", "mediastinal", "an", "opacity", "effusion", "aorta", "focal", "for", "clear", "are", "with", "pneumothorax", "focal", "free"]]}, {"image_id": "3869_IM-1962-1001.png", "caption": [["<start>", "stable", "and"]]}, {"image_id": "3895_IM-1977-1001.png", "caption": [["<start>", "the", "view", "junction", "chest"]]}, {"image_id": "3921_IM-1995-1001.png", "caption": [["<start>", "the", "lung", "examination", "within", "quadrant", "appear", "are", "a"]]}, {"image_id": "3942_IM-2013-1001.png", "caption": [["<start>", "the", "lungs", "is"]]}, {"image_id": "3961_IM-2026-2001.png", "caption": [["<start>", "nodular", "size", "silhouette", "status", "there", "size", "of", "pulmonary", "contour", "evidence", "not"]]}]